cmdc/__init__.py
cmdc/__main__.py
cmdc/cli.py
cmdc/config_manager.py
cmdc/file_browser.py
cmdc/output_handler.py
cmdc/prompt_style.py
cmdc/utils.py
pycmdc-1.3.0.dist-info/LICENSE
pycmdc-1.3.0.dist-info/METADATA
pycmdc-1.3.0.dist-info/WHEEL
pycmdc-1.3.0.dist-info/entry_points.txt
pycmdc-1.3.0.dist-info/RECORD
