Metadata-Version: 2.3
Name: pycmdc
Version: 1.3.0
Summary: Ditch the copy-paste madness - browse, select, and format code for LLMs, keyboard-only.
License: MIT
Author: 0xmrwn
Author-email: niches-anode0k@icloud.com
Requires-Python: >=3.9,<4.0
Classifier: License :: OSI Approved :: MIT License
Classifier: Programming Language :: Python :: 3
Classifier: Programming Language :: Python :: 3.9
Classifier: Programming Language :: Python :: 3.10
Classifier: Programming Language :: Python :: 3.11
Classifier: Programming Language :: Python :: 3.12
Classifier: Programming Language :: Python :: 3.13
Requires-Dist: inquirerpy (>=0.3.4,<0.4.0)
Requires-Dist: pyperclip (>=1.9.0,<2.0.0)
Requires-Dist: rich (>=14.0.0,<14.1.0)
Requires-Dist: tiktoken (>=0.9.0,<0.10.0)
Requires-Dist: toml (>=0.10.2,<0.11.0)
Requires-Dist: typer (>=0.16.0,<0.17.0)
